{
  "slug": "indonesia",
  "name": "Indonesia",
  "adjective": "Indonesian",
  "treatyYear": 1968,
  "visaValidity": "2 years",
  "annualIssuances": 150,
  "consulate": "U.S. Embassy Jakarta",
  "metaTitle": "E-2 Visa for Indonesian Nationals | Watson Immigration Law",
  "metaDescription": "E-2 Treaty Investor Visa information for Indonesia nationals. Treaty status, visa validity, investment requirements, and consulate processing guidance from Watson Immigration Law.",
  "h1": "E-2 Visa for Indonesian Nationals",
  "intro": "",
  "sections": [],
  "faqs": [],
  "relatedCountries": [],
  "relatedCities": []
}