{
  "slug": "senegal",
  "name": "Senegal",
  "adjective": "Senegalese",
  "treatyYear": 1990,
  "visaValidity": "3 months",
  "annualIssuances": null,
  "consulate": "U.S. Embassy Dakar",
  "metaTitle": "E-2 Visa for Senegalese Nationals | Watson Immigration Law",
  "metaDescription": "E-2 Treaty Investor Visa information for Senegal nationals. Treaty status, visa validity, investment requirements, and consulate processing guidance from Watson Immigration Law.",
  "h1": "E-2 Visa for Senegalese Nationals",
  "intro": "",
  "sections": [],
  "faqs": [],
  "relatedCountries": [],
  "relatedCities": []
}