{
  "slug": "orlando",
  "name": "Orlando",
  "state": "Florida",
  "stateCode": "FL",
  "metaTitle": "E-2 Visa Attorney in Orlando, FL | Watson Immigration Law",
  "metaDescription": "E-2 Treaty Investor Visa attorneys serving Orlando, Florida. Expert guidance for international investors opening or acquiring businesses in Orlando.",
  "h1": "E-2 Treaty Investor Visa Attorney in Orlando, FL",
  "intro": "",
  "sections": [],
  "stateTax": "",
  "uscisOffice": "",
  "industries": [],
  "topNationalities": [],
  "faqs": [],
  "relatedCities": []
}